README.md
setup.py
ARCHIT/__init__.py
ARCHIT/topsis.py
Topsis_Archit_101917119.egg-info/PKG-INFO
Topsis_Archit_101917119.egg-info/SOURCES.txt
Topsis_Archit_101917119.egg-info/dependency_links.txt
Topsis_Archit_101917119.egg-info/top_level.txt