Metadata-Version: 2.1
Name: Topsis-Archit-101917119
Version: 0.0.5
Summary: Topsis
Home-page: UNKNOWN
Author: Archit
Author-email: <architvashist006@gmail.com>
License: UNKNOWN
Keywords: python,Topsis
Platform: UNKNOWN
Classifier: Development Status :: 1 - Planning
Classifier: Intended Audience :: Developers
Classifier: Programming Language :: Python :: 3
Classifier: Operating System :: Unix
Classifier: Operating System :: MacOS :: MacOS X
Classifier: Operating System :: Microsoft :: Windows
